npi_field/__init__.py
npi_field/formfields.py
npi_field/modelfields.py
npi_field/validators.py
npi_field/widgets.py
django_npi_field-0.2.2.dist-info/LICENSE
django_npi_field-0.2.2.dist-info/METADATA
django_npi_field-0.2.2.dist-info/WHEEL
django_npi_field-0.2.2.dist-info/RECORD
