Metadata-Version: 2.1
Name: django-npi-field
Version: 0.2.2
Summary: Creates a Django field for U.S. National Provider Identifier numbers
Home-page: https://github.com/nullandvoid-digital/django-npi-field
License: MIT
Keywords: django
Author: Kyle Jensen
Author-email: kyle@nullandvoid.digital
Requires-Python: >=3.8,<4.0
Classifier: Environment :: Web Environment
Classifier: Framework :: Django
Classifier: Intended Audience :: Developers
Classifier: License :: OSI Approved :: MIT License
Classifier: Operating System :: OS Independent
Classifier: Programming Language :: Python
Classifier: Programming Language :: Python :: 3
Classifier: Programming Language :: Python :: 3.8
Classifier: Programming Language :: Python :: 3.9
Classifier: Programming Language :: Python :: 3.10
Classifier: Programming Language :: Python :: 3.11
Classifier: Programming Language :: Python :: 3.12
Classifier: Programming Language :: Python :: Implementation :: CPython
Classifier: Topic :: Internet :: WWW/HTTP
Classifier: Topic :: Internet :: WWW/HTTP :: Dynamic Content
Requires-Dist: django (>=4.0)
Project-URL: Repository, https://github.com/nullandvoid-digital/django-npi-field
